shatter_api/__init__.py
shatter_api/api/__init__.py
shatter_api/api/api.py
shatter_api/api/descriptors.py
shatter_api/api/endpoints.py
shatter_api/api/mapping.py
shatter_api/backend.py
shatter_api/call_builder.py
shatter_api/middlewear.py
shatter_api/request/__init__.py
shatter_api/request/request.py
shatter_api/request/request_info.py
shatter_api/responses/__init__.py
shatter_api/responses/response_types.py
shatter_api/responses/responses.py
shatter_api/responses/utils.py
shatter_api/statuses.py
shatter_api/type_extraction.py
shatter_api/utils.py
shatter_api-0.3.4.dist-info/LICENSE
shatter_api-0.3.4.dist-info/METADATA
shatter_api-0.3.4.dist-info/WHEEL
shatter_api-0.3.4.dist-info/RECORD
