Metadata-Version: 2.3
Name: shatter-api
Version: 0.3.4
Summary: A self-hosted, pluggable mirror for secret stores providing a consistent API & offline access for your secrets.
License: MIT
Author: ripple
Author-email: github@ripplefcl.com>, tigattack <?
Requires-Python: >=3.13
Classifier: License :: OSI Approved :: MIT License
Classifier: Programming Language :: Python :: 3
Classifier: Programming Language :: Python :: 3.13
Requires-Dist: fastapi (>=0.115.12,<0.116.0)
Requires-Dist: pydantic (>=2.11.5,<3.0.0)
Requires-Dist: pyyaml (>=6.0.2,<7.0.0)
Requires-Dist: typeguard (>=4.4.4,<5.0.0)
